jpipe_runner/GraphWorkflowVisualizer.py
jpipe_runner/__init__.py
jpipe_runner/__main__.py
jpipe_runner/enums.py
jpipe_runner/exceptions.py
jpipe_runner/framework/__init__.py
jpipe_runner/framework/context.py
jpipe_runner/framework/decorators/__init__.py
jpipe_runner/framework/decorators/contribution_decorator.py
jpipe_runner/framework/decorators/jpipe_decorator.py
jpipe_runner/framework/decorators/skip_decorator.py
jpipe_runner/framework/engine.py
jpipe_runner/framework/logger.py
jpipe_runner/framework/validators.py
jpipe_runner/runner.py
jpipe_runner/runtime.py
jpipe_runner/utils.py
jpipe_runner-3.0.0.dist-info/LICENSE
jpipe_runner-3.0.0.dist-info/METADATA
jpipe_runner-3.0.0.dist-info/WHEEL
jpipe_runner-3.0.0.dist-info/entry_points.txt
jpipe_runner-3.0.0.dist-info/RECORD
