Metadata-Version: 2.3
Name: jpipe-runner
Version: 3.0.0
Summary: A Justification Runner designed for jPipe.
License: MIT
Keywords: justification,pipeline,ML,AI
Author: Jason Lyu
Author-email: xjasonlyu@gmail.com
Requires-Python: >=3.11
Classifier: License :: OSI Approved :: MIT License
Classifier: Operating System :: OS Independent
Classifier: Programming Language :: Python :: 3
Classifier: Programming Language :: Python :: 3.11
Classifier: Programming Language :: Python :: 3.12
Classifier: Programming Language :: Python :: 3.13
Provides-Extra: docs
Provides-Extra: full
Provides-Extra: gui
Requires-Dist: matplotlib (==3.10.5) ; extra == "gui" or extra == "full"
Requires-Dist: networkx (==3.5)
Requires-Dist: pygraphviz (==1.14)
Requires-Dist: pyyaml (==6.0.2)
Requires-Dist: sphinx (==8.1.3) ; extra == "docs" or extra == "full"
Project-URL: Homepage, https://github.com/jpipe-mcscert/jpipe-runner
